{
    "Modules": {
        "Core": {
            "Compiled": "Yes",
            "Compiled Times": 2
        }
    },
    "ObjArchives": [
        {
            "size": 292926,
            "archive": "archive.39/_21239_archive_1.a",
            "objects": [
                [
                    "fsHFs_d.o",
                    292926
                ]
            ]
        }
    ],
    "CompUnits": {
        "fsHFs_d": {
            "mod": "Core",
            "bytes": 292926,
            "out": "fsHFs_d.o",
            "mode": 4,
            "checksum": 4294967295,
            "archive": "archive.39/_21239_archive_1.a"
        }
    },
    "reusePaths": {}
}